Metadata-Version: 2.1
Name: mobsecco
Version: 0.1
Summary: Clone Cordova application for fun and bypassing security restrictions for pentesting
Home-page: https://github.com/Anof-cyber/MobSecco
Author: Sourav Kalal
Author-email: kalalsourav20@gmail.com
License: MIT license
Keywords: mobsecco,bug bounty,android,pentesting,security
Classifier: Development Status :: 5 - Production/Stable
Classifier: Intended Audience :: Developers
Classifier: Intended Audience :: Information Technology
Classifier: Operating System :: OS Independent
Classifier: Topic :: Security
Classifier: License :: OSI Approved :: MIT License
Classifier: Programming Language :: Python :: 3.4
Requires-Python: >=3.6
License-File: LICENSE
